tmxutil/__init__.py
tmxutil/__main__.py
tmxutil/cli.py
tmxutil/interactive.py
tmxutil/types.py
tmxutil/utils.py
tmxutil/filters/__init__.py
tmxutil/filters/deduplicate.py
tmxutil/filters/ipc.py
tmxutil/formats/__init__.py
tmxutil/formats/count.py
tmxutil/formats/json.py
tmxutil/formats/pickle.py
tmxutil/formats/tab.py
tmxutil/formats/tmx.py
tmxutil/formats/txt.py
tmxutil-1.3.dist-info/LICENSE
tmxutil-1.3.dist-info/METADATA
tmxutil-1.3.dist-info/WHEEL
tmxutil-1.3.dist-info/entry_points.txt
tmxutil-1.3.dist-info/top_level.txt
tmxutil-1.3.dist-info/RECORD
