Metadata-Version: 2.1
Name: tmxutil
Version: 1.3
Summary: Tool to create, augment, filter and generally work with TMX files.
Home-page: https://github.com/paracrawl/tmxutil
Author: Jelmer van der Linde
Author-email: jelmer@ikhoefgeen.nl
Project-URL: Bug Tracker, https://github.com/paracrawl/tmxutil/issues
Classifier: Programming Language :: Python :: 3
Classifier: License :: OSI Approved :: MIT License
Classifier: Operating System :: OS Independent
Requires-Python: >=3.6
License-File: LICENSE
